{
  "id": "vocabble-2026-05-22",
  "date": "2026-05-22",
  "size": 8,
  "fleetLengths": [6, 5, 4, 4, 3, 3],
  "solution": [
    ["", "P", "U", "S", "H", "", "", ""],
    ["L", "E", "G", "", "", "", "", ""],
    ["A", "N", "A", "T", "U", "R", "E", ""],
    ["I", "", "", "", "", "", "", "T"],
    ["M", "F", "", "", "", "", "", "H"],
    ["", "O", "", "", "", "", "", "I"],
    ["", "R", "", "", "", "", "", "R"],
    ["", "M", "", "", "", "", "", "D"]
  ],
  "puzzle": [
    ["", "P", "", "S", "", "", "", ""],
    ["", "E", "", "", "", "", "", ""],
    ["", "N", "", "", "U", "", "E", ""],
    ["", "", "", "", "", "", "", ""],
    ["M", "", "", "", "", "", "", "H"],
    ["", "", "", "", "", "", "", ""],
    ["", "R", "", "", "", "", "", "R"],
    ["", "", "", "", "", "", "", ""]
  ],
  "topWord": "MEASURED",
  "sideWord": "PLATFORM",
  "topVisible": [false, true, true, false, false, true, true, false],
  "sideVisible": [true, false, false, true, false, true, true, false],
  "ships": [
    {
      "word": "NATURE",
      "length": 6,
      "row": 3,
      "col": 2,
      "direction": "H"
    },
    {
      "word": "THIRD",
      "length": 5,
      "row": 4,
      "col": 8,
      "direction": "V"
    },
    {
      "word": "FORM",
      "length": 4,
      "row": 5,
      "col": 2,
      "direction": "V"
    },
    {
      "word": "PUSH",
      "length": 4,
      "row": 1,
      "col": 2,
      "direction": "H"
    },
    {
      "word": "LEG",
      "length": 3,
      "row": 2,
      "col": 1,
      "direction": "H"
    },
    {
      "word": "AIM",
      "length": 3,
      "row": 3,
      "col": 1,
      "direction": "V"
    }
  ],
  "difficulty": {
    "label": "medium-hard",
    "hiddenLetters": 15,
    "hiddenEdges": 8,
    "givenLetters": 10
  },
  "validation": {
    "ok": true,
    "dictionary_ok": true,
    "row_edge_ok": true,
    "col_edge_ok": true
  }
}
